education_inquiry/__init__.py
education_inquiry/main.py
tests/__init__.py
tests/testing.py
inquirybot-0.2.dist-info/METADATA
inquirybot-0.2.dist-info/WHEEL
inquirybot-0.2.dist-info/top_level.txt
inquirybot-0.2.dist-info/RECORD
