Metadata-Version: 2.1
Name: inquirybot
Version: 0.2
Requires-Dist: joblib
Requires-Dist: pandas
Requires-Dist: numpy
Requires-Dist: nltk
Requires-Dist: torch
Requires-Dist: transformers
Requires-Dist: spellchecker
Requires-Dist: gensim
Requires-Dist: scikit-learn
